{"phase":"N","release":"commission-v1.1-phaseN-remove-legacy-transport-2026-07-02-r1","releaseStamp":"commission-v1.1-phaseN-remove-legacy-transport-2026-07-02-r1","assetStamp":"asset-manifest-commission-v1.1-phaseN-remove-legacy-transport-2026-07-02-r1","releaseGate":"tools/phaseN_legacy_transport_gate.py","transportMode":"phaseN-vercel-proxy-only-no-jsonp-no-bridge-no-login-iframe","apiContractOwner":"gas-backend/Code_20_Router.gs::_apiRouteRegistry_","writeSchemaOwner":"Code_20_Router.WRITE_SCHEMA_BY_METHOD","writeRouteCount":27,"writeSchemaCount":27,"singleSourcePolicy":"docs/SINGLE_SOURCE_POLICY.md","generatedMirrorPolicy":"edit gas-backend/Scripts_*.html, then run tools/sync_frontend_partials.py; do not edit github-pages/partials directly","forbiddenPageScriptCalls":["AppApi.call","AppPageController.api","Utils.apiRunner","google.script.run"],"phaseNLegacyTransportRemoved":true,"legacyJsonpTransportRemoved":true,"legacyGasBridgeTransportRemoved":true,"legacyLoginPostIframeRemoved":true,"securityFlags":{"fastLoginJsonp":false,"allowAssumedBridgeReady":false,"requireBridgeReadyMessage":true,"loginViaVercelProxy":true},"runtimePolicies":{"writeCacheInvalidation":true,"runtimeSessionStorageCacheInvalidation":true,"activePageRefreshAfterWrite":true,"strictActionTokenFrontendMirror":true,"uiCssCompactionSafetyGate":true,"reportTrackPageCacheTtlMs":180000},"sizeReduction":{"baselineSourceBytes":5344039,"previousSourceBytesAfterUnicodeReduction":4843114,"notes":"Manifest compacted and build gate hardened; no API/route/schema/business logic changes.","currentSourceBytes":4826739,"currentSourceBytesReducedFromPhaseNBaseline":518749,"phase1TotalSourceBudget":4860000,"previousPhase1SourceBytes":4834283,"currentSourceBytesReducedFromPhase1":8993,"phase2TotalSourceBudget":4830000,"phase2CoreRuntimeBytes":396329,"phase2CoreRuntimeMirrorBytes":396423,"previousPhase2SourceBytes":4825290,"currentSourceBytesReducedFromPhase2":1421,"phase3TotalSourceBudget":4825000,"phase3Code30DomainCasesBytes":333822,"previousPhase3SourceBytes":4823869,"phase4TotalSourceBudget":4825000,"phase4SizeGate":"tools/phaseN_legacy_transport_gate.py::PHASE4_SIZE_BUDGETS","phase4Code30DomainCasesBudgetBytes":333900,"phase4Code32BudgetBudgetBytes":235900,"phase4SourceDeltaFromPhase3":833,"previousPhase4SourceBytes":4824702,"phase5TotalSourceBudget":4827000,"phase5SourceDeltaFromPhase4":2037,"phase5SizeGate":"tools/phaseN_legacy_transport_gate.py::PHASE5_SIZE_BUDGETS","phase5Code32BudgetBudgetBytes":235900,"phase5DynamicGeneratedFilesExcluded":["github-pages/vercel-env.generated.js"],"phase5DeterministicSourceBudget":4827000},"currentKnownLargestFiles":["gas-backend/Scripts_Core_Runtime.html","gas-backend/Code_30_Domain_Cases.gs","gas-backend/Index.html","gas-backend/Scripts_Page_Meeting.html","gas-backend/Code_32_Domain_Budget.gs"],"nextDebtTargets":["Phase 5: lower Scripts_Page_Meeting.html after helper deduplication","Phase 5: continue Code_30_Domain_Cases.gs toward 310KB without new API","keep BudgetDomain as the only budget hydration owner"],"updatedAt":"2026-07-04T00:00:00+07:00","phase1Hardening":{"noApiAdded":true,"noFilesAdded":true,"businessLogicChanged":false,"uiUxChanged":false},"phase2RuntimeSlimming":{"noApiAdded":true,"noFilesAdded":true,"businessLogicChanged":false,"uiUxChanged":false},"phase3DomainConsolidation":{"noApiAdded":true,"noFilesAdded":true,"businessLogicChanged":false,"uiUxChanged":false},"phase4BudgetOwnerConsolidation":{"owner":"BudgetDomain.getDashboardSummaryForDashboard","dashboardBudgetImportsOwnershipRemoved":true,"directDashboardFallbackRemoved":true,"noApiAdded":true,"noFilesAdded":true,"businessLogicChanged":false,"uiUxChanged":false,"writeSchemaChanged":false,"routeRegistryChanged":false},"subPhase":"Phase 5 build hotfix: deterministic size gate for Vercel env","phase5DataLoadingPerformance":true,"phase5Changes":{"dashboardBudgetHydration":"cacheable 600s payload; no hard forceFresh/noCache/bypassCache","apiBudgetGetSummaryDashboardHydration":"preserves explicit freshness flags only","hotReadRouteCacheTtls":["apiSearchCasesLite","apiGetTracking","apiGetPeoplePageBundle","apiBudgetGetSummary"],"filesAdded":0,"apiAdded":0,"uiDomChanged":false,"businessLogicChanged":false},"phase5BuildFix":true,"phase5BuildFixReason":"Vercel regenerates github-pages/vercel-env.generated.js with deploy-specific public metadata; the Phase 5 total source gate now excludes this dynamic generated file."}